forecast_in_a_box-0.4.3.dist-info/licenses/LICENSE
forecastbox/__init__.py
forecastbox/_version.py
forecastbox/config.py
forecastbox/core.py
forecastbox/entrypoint.py
forecastbox/api/__init__.py
forecastbox/api/execution.py
forecastbox/api/fable.py
forecastbox/api/updates.py
forecastbox/api/utils.py
forecastbox/api/visualisation.py
forecastbox/api/routers/__init__.py
forecastbox/api/routers/admin.py
forecastbox/api/routers/auth.py
forecastbox/api/routers/execution.py
forecastbox/api/routers/fable.py
forecastbox/api/routers/gateway.py
forecastbox/api/routers/job.py
forecastbox/api/routers/model.py
forecastbox/api/routers/product.py
forecastbox/api/routers/schedule.py
forecastbox/api/scheduling/__init__.py
forecastbox/api/scheduling/dt_utils.py
forecastbox/api/scheduling/job_utils.py
forecastbox/api/scheduling/scheduler_thread.py
forecastbox/api/types/__init__.py
forecastbox/api/types/base.py
forecastbox/api/types/fable.py
forecastbox/auth/oidc.py
forecastbox/auth/users.py
forecastbox/db/__init__.py
forecastbox/db/core.py
forecastbox/db/job.py
forecastbox/db/migrations.py
forecastbox/db/model.py
forecastbox/db/schedule.py
forecastbox/db/user.py
forecastbox/models/__init__.py
forecastbox/models/globe.py
forecastbox/models/metadata.py
forecastbox/models/model.py
forecastbox/models/nested.py
forecastbox/models/utils.py
forecastbox/products/__init__.py
forecastbox/products/definitions.py
forecastbox/products/export.py
forecastbox/products/forecast.py
forecastbox/products/generic.py
forecastbox/products/interfaces.py
forecastbox/products/pproc.py
forecastbox/products/product.py
forecastbox/products/registry.py
forecastbox/products/standard.py
forecastbox/products/thermal.py
forecastbox/products/ensemble/__init__.py
forecastbox/products/ensemble/base.py
forecastbox/products/ensemble/ens_stats.py
forecastbox/products/ensemble/quantiles.py
forecastbox/products/ensemble/threshold.py
forecastbox/products/ensemble/definitions/quantiles.yaml
forecastbox/products/ensemble/definitions/threshold_probability.yaml
forecast_in_a_box-0.4.3.dist-info/METADATA
forecast_in_a_box-0.4.3.dist-info/WHEEL
forecast_in_a_box-0.4.3.dist-info/top_level.txt
forecast_in_a_box-0.4.3.dist-info/RECORD
