Metadata-Version: 2.4
Name: forecast-in-a-box
Version: 0.4.3
Summary: Weather Forecast in a Box
Author-email: "European Centre for Medium-Range Weather Forecasts (ECMWF)" <software.support@ecmwf.int>
License-Expression: Apache-2.0
Project-URL: Source code, https://github.com/ecmwf/forecast-in-a-box
Classifier: Programming Language :: Python :: 3 :: Only
Classifier: Programming Language :: Python :: 3.11
Classifier: Programming Language :: Python :: 3.12
Classifier: Programming Language :: Python :: 3.13
Requires-Python: >=3.11
License-File: LICENSE
Requires-Dist: aiosqlite
Requires-Dist: anemoi-inference==0.8.3
Requires-Dist: anemoi-plugins-ecmwf-inference[opendata,polytope]>=0.1.17
Requires-Dist: anemoi-utils>=0.4.36
Requires-Dist: apscheduler
Requires-Dist: cloudpickle
Requires-Dist: earthkit-workflows>=0.4.7
Requires-Dist: earthkit-workflows-anemoi>=0.3.12
Requires-Dist: earthkit-workflows-pproc
Requires-Dist: fastapi
Requires-Dist: fastapi-users[oauth]
Requires-Dist: fastapi-users-db-sqlalchemy
Requires-Dist: httpx<1
Requires-Dist: httpx-oauth
Requires-Dist: jinja2
Requires-Dist: mir-python==1.27.10.5
Requires-Dist: multiolib==2.7.1.5
Requires-Dist: orjson
Requires-Dist: pproc
Requires-Dist: psutil
Requires-Dist: pydantic-settings
Requires-Dist: pyrsistent
Requires-Dist: python-multipart
Requires-Dist: qubed==0.1.12
Requires-Dist: sse-starlette
Requires-Dist: toml
Requires-Dist: uvicorn
Provides-Extra: all
Requires-Dist: forecast-in-a-box[dev,plots,thermo]; extra == "all"
Provides-Extra: plots
Requires-Dist: earthkit-plots>=0.3.5; extra == "plots"
Requires-Dist: earthkit-plots-default-styles>=0.1; extra == "plots"
Provides-Extra: thermo
Requires-Dist: thermofeel>=2.1.1; extra == "thermo"
Provides-Extra: webmars
Requires-Dist: ecmwf-api-client>=1.6.5; extra == "webmars"
Dynamic: license-file
